{
  "timestamp": "2025-08-14T12:57:15.000353",
  "summary": {
    "total_layers": 7,
    "total_features": 775291,
    "status_counts": {
      "GOOD": 7
    }
  },
  "layers": {
    "roads": {
      "layer_name": "roads",
      "total_features": 86085,
      "status": "GOOD",
      "issues": [],
      "warnings": [],
      "recommendations": [],
      "statistics": {
        "feature_count": 86085,
        "crs": "{\"$schema\": \"https://proj.org/schemas/v0.7/projjson.schema.json\", \"type\": \"GeographicCRS\", \"name\": \"WGS 84\", \"datum_ensemble\": {\"name\": \"World Geodetic System 1984 ensemble\", \"members\": [{\"name\": \"World Geodetic System 1984 (Transit)\"}, {\"name\": \"World Geodetic System 1984 (G730)\"}, {\"name\": \"World Geodetic System 1984 (G873)\"}, {\"name\": \"World Geodetic System 1984 (G1150)\"}, {\"name\": \"World Geodetic System 1984 (G1674)\"}, {\"name\": \"World Geodetic System 1984 (G1762)\"}, {\"name\": \"World Geodetic System 1984 (G2139)\"}, {\"name\": \"World Geodetic System 1984 (G2296)\"}], \"ellipsoid\": {\"name\": \"WGS 84\", \"semi_major_axis\": 6378137, \"inverse_flattening\": 298.257223563}, \"accuracy\": \"2.0\", \"id\": {\"authority\": \"EPSG\", \"code\": 6326}}, \"coordinate_system\": {\"subtype\": \"ellipsoidal\", \"axis\": [{\"name\": \"Geodetic latitude\", \"abbreviation\": \"Lat\", \"direction\": \"north\", \"unit\": \"degree\"}, {\"name\": \"Geodetic longitude\", \"abbreviation\": \"Lon\", \"direction\": \"east\", \"unit\": \"degree\"}]}, \"scope\": \"Horizontal component of 3D system.\", \"area\": \"World.\", \"bbox\": {\"south_latitude\": -90, \"west_longitude\": -180, \"north_latitude\": 90, \"east_longitude\": 180}, \"id\": {\"authority\": \"EPSG\", \"code\": 4326}}",
        "columns": [
          "osmid",
          "name",
          "highway",
          "maxspeed",
          "lanes",
          "surface",
          "oneway",
          "bridge",
          "tunnel",
          "access",
          "geometry",
          "length_m",
          "category"
        ],
        "memory_usage_mb": 33.92
      },
      "geometry_analysis": {
        "geometry_types": {
          "MultiLineString": 86077,
          "GeometryCollection": 8
        },
        "invalid_geometries": 0,
        "empty_geometries": 0,
        "null_geometries": 0,
        "topology_issues": []
      },
      "attribute_analysis": {
        "total_columns": 12,
        "null_analysis": {
          "osmid": {
            "null_count": 0,
            "null_percentage": 0.0
          },
          "name": {
            "null_count": 41914,
            "null_percentage": 48.7
          },
          "highway": {
            "null_count": 0,
            "null_percentage": 0.0
          },
          "maxspeed": {
            "null_count": 45763,
            "null_percentage": 53.2
          },
          "lanes": {
            "null_count": 67529,
            "null_percentage": 78.4
          },
          "surface": {
            "null_count": 22425,
            "null_percentage": 26.0
          },
          "oneway": {
            "null_count": 69752,
            "null_percentage": 81.0
          },
          "bridge": {
            "null_count": 84823,
            "null_percentage": 98.5
          },
          "tunnel": {
            "null_count": 85378,
            "null_percentage": 99.2
          },
          "access": {
            "null_count": 77678,
            "null_percentage": 90.2
          },
          "length_m": {
            "null_count": 0,
            "null_percentage": 0.0
          },
          "category": {
            "null_count": 0,
            "null_percentage": 0.0
          }
        },
        "data_types": {
          "osmid": "int64",
          "name": "object",
          "highway": "object",
          "maxspeed": "object",
          "lanes": "object",
          "surface": "object",
          "oneway": "object",
          "bridge": "object",
          "tunnel": "object",
          "access": "object",
          "length_m": "float64",
          "category": "object"
        },
        "unique_values": {}
      },
      "spatial_analysis": {
        "bounding_box": [
          9.0,
          48.599998474121094,
          9.399999618530273,
          48.900001525878906
        ],
        "extent_analysis": {
          "within_stuttgart": false
        },
        "density_analysis": {
          "features_per_km2": 58.22
        },
        "size_analysis": {
          "lines": {
            "count": 86077,
            "min_length_m": 1.0046822266327389,
            "max_length_m": 5657.3650179396345,
            "mean_length_m": 107.74907996473073,
            "tiny_features": 0
          }
        }
      }
    },
    "buildings": {
      "layer_name": "buildings",
      "total_features": 379611,
      "status": "GOOD",
      "issues": [],
      "warnings": [],
      "recommendations": [],
      "statistics": {
        "feature_count": 379611,
        "crs": "{\"$schema\": \"https://proj.org/schemas/v0.7/projjson.schema.json\", \"type\": \"GeographicCRS\", \"name\": \"WGS 84\", \"datum_ensemble\": {\"name\": \"World Geodetic System 1984 ensemble\", \"members\": [{\"name\": \"World Geodetic System 1984 (Transit)\"}, {\"name\": \"World Geodetic System 1984 (G730)\"}, {\"name\": \"World Geodetic System 1984 (G873)\"}, {\"name\": \"World Geodetic System 1984 (G1150)\"}, {\"name\": \"World Geodetic System 1984 (G1674)\"}, {\"name\": \"World Geodetic System 1984 (G1762)\"}, {\"name\": \"World Geodetic System 1984 (G2139)\"}, {\"name\": \"World Geodetic System 1984 (G2296)\"}], \"ellipsoid\": {\"name\": \"WGS 84\", \"semi_major_axis\": 6378137, \"inverse_flattening\": 298.257223563}, \"accuracy\": \"2.0\", \"id\": {\"authority\": \"EPSG\", \"code\": 6326}}, \"coordinate_system\": {\"subtype\": \"ellipsoidal\", \"axis\": [{\"name\": \"Geodetic latitude\", \"abbreviation\": \"Lat\", \"direction\": \"north\", \"unit\": \"degree\"}, {\"name\": \"Geodetic longitude\", \"abbreviation\": \"Lon\", \"direction\": \"east\", \"unit\": \"degree\"}]}, \"scope\": \"Horizontal component of 3D system.\", \"area\": \"World.\", \"bbox\": {\"south_latitude\": -90, \"west_longitude\": -180, \"north_latitude\": 90, \"east_longitude\": 180}, \"id\": {\"authority\": \"EPSG\", \"code\": 4326}}",
        "columns": [
          "osmid",
          "name",
          "building",
          "levels",
          "height",
          "geometry",
          "area_m2",
          "category"
        ],
        "memory_usage_mb": 78.96
      },
      "geometry_analysis": {
        "geometry_types": {
          "Polygon": 379396,
          "MultiPolygon": 84,
          "LineString": 66,
          "GeometryCollection": 56,
          "MultiLineString": 9
        },
        "invalid_geometries": 0,
        "empty_geometries": 0,
        "null_geometries": 0,
        "topology_issues": []
      },
      "attribute_analysis": {
        "total_columns": 7,
        "null_analysis": {
          "osmid": {
            "null_count": 0,
            "null_percentage": 0.0
          },
          "name": {
            "null_count": 370007,
            "null_percentage": 97.5
          },
          "building": {
            "null_count": 0,
            "null_percentage": 0.0
          },
          "levels": {
            "null_count": 379609,
            "null_percentage": 100.0
          },
          "height": {
            "null_count": 378446,
            "null_percentage": 99.7
          },
          "area_m2": {
            "null_count": 0,
            "null_percentage": 0.0
          },
          "category": {
            "null_count": 0,
            "null_percentage": 0.0
          }
        },
        "data_types": {
          "osmid": "int64",
          "name": "object",
          "building": "object",
          "levels": "object",
          "height": "object",
          "area_m2": "float64",
          "category": "object"
        },
        "unique_values": {}
      },
      "spatial_analysis": {
        "bounding_box": [
          9.0,
          48.60000228881836,
          9.399999618530273,
          48.900001525878906
        ],
        "extent_analysis": {
          "within_stuttgart": false
        },
        "density_analysis": {
          "features_per_km2": 256.75
        },
        "size_analysis": {
          "polygons": {
            "count": 379480,
            "min_area_m2": 1.0080397933994367,
            "max_area_m2": 76170.63381906677,
            "mean_area_m2": 177.10274977787762,
            "tiny_features": 0
          },
          "lines": {
            "count": 75,
            "min_length_m": 0.1399765059194992,
            "max_length_m": 26.659231979477326,
            "mean_length_m": 8.171515424013924,
            "tiny_features": 9
          }
        }
      }
    },
    "landuse": {
      "layer_name": "landuse",
      "total_features": 30772,
      "status": "GOOD",
      "issues": [],
      "warnings": [],
      "recommendations": [],
      "statistics": {
        "feature_count": 30772,
        "crs": "{\"$schema\": \"https://proj.org/schemas/v0.7/projjson.schema.json\", \"type\": \"GeographicCRS\", \"name\": \"WGS 84\", \"datum_ensemble\": {\"name\": \"World Geodetic System 1984 ensemble\", \"members\": [{\"name\": \"World Geodetic System 1984 (Transit)\"}, {\"name\": \"World Geodetic System 1984 (G730)\"}, {\"name\": \"World Geodetic System 1984 (G873)\"}, {\"name\": \"World Geodetic System 1984 (G1150)\"}, {\"name\": \"World Geodetic System 1984 (G1674)\"}, {\"name\": \"World Geodetic System 1984 (G1762)\"}, {\"name\": \"World Geodetic System 1984 (G2139)\"}, {\"name\": \"World Geodetic System 1984 (G2296)\"}], \"ellipsoid\": {\"name\": \"WGS 84\", \"semi_major_axis\": 6378137, \"inverse_flattening\": 298.257223563}, \"accuracy\": \"2.0\", \"id\": {\"authority\": \"EPSG\", \"code\": 6326}}, \"coordinate_system\": {\"subtype\": \"ellipsoidal\", \"axis\": [{\"name\": \"Geodetic latitude\", \"abbreviation\": \"Lat\", \"direction\": \"north\", \"unit\": \"degree\"}, {\"name\": \"Geodetic longitude\", \"abbreviation\": \"Lon\", \"direction\": \"east\", \"unit\": \"degree\"}]}, \"scope\": \"Horizontal component of 3D system.\", \"area\": \"World.\", \"bbox\": {\"south_latitude\": -90, \"west_longitude\": -180, \"north_latitude\": 90, \"east_longitude\": 180}, \"id\": {\"authority\": \"EPSG\", \"code\": 4326}}",
        "columns": [
          "osmid",
          "landuse",
          "natural",
          "geometry",
          "area_m2",
          "category"
        ],
        "memory_usage_mb": 4.93
      },
      "geometry_analysis": {
        "geometry_types": {
          "Polygon": 30509,
          "MultiPolygon": 243,
          "LineString": 18,
          "GeometryCollection": 1,
          "MultiLineString": 1
        },
        "invalid_geometries": 0,
        "empty_geometries": 0,
        "null_geometries": 0,
        "topology_issues": []
      },
      "attribute_analysis": {
        "total_columns": 5,
        "null_analysis": {
          "osmid": {
            "null_count": 0,
            "null_percentage": 0.0
          },
          "landuse": {
            "null_count": 4637,
            "null_percentage": 15.1
          },
          "natural": {
            "null_count": 26135,
            "null_percentage": 84.9
          },
          "area_m2": {
            "null_count": 0,
            "null_percentage": 0.0
          },
          "category": {
            "null_count": 0,
            "null_percentage": 0.0
          }
        },
        "data_types": {
          "osmid": "int64",
          "landuse": "object",
          "natural": "object",
          "area_m2": "float64",
          "category": "object"
        },
        "unique_values": {}
      },
      "spatial_analysis": {
        "bounding_box": [
          9.0,
          48.599998474121094,
          9.39999771118164,
          48.900001525878906
        ],
        "extent_analysis": {
          "within_stuttgart": false
        },
        "density_analysis": {
          "features_per_km2": 20.81
        },
        "size_analysis": {
          "polygons": {
            "count": 30752,
            "min_area_m2": 1.41428178493827,
            "max_area_m2": 25598065.93569422,
            "mean_area_m2": 28616.11385310535,
            "tiny_features": 0
          },
          "lines": {
            "count": 19,
            "min_length_m": 8.074360550178888,
            "max_length_m": 111.5466062278976,
            "mean_length_m": 37.376944518765235,
            "tiny_features": 0
          }
        }
      }
    },
    "cycle": {
      "layer_name": "cycle",
      "total_features": 124351,
      "status": "GOOD",
      "issues": [],
      "warnings": [],
      "recommendations": [],
      "statistics": {
        "feature_count": 124351,
        "crs": "{\"$schema\": \"https://proj.org/schemas/v0.7/projjson.schema.json\", \"type\": \"GeographicCRS\", \"name\": \"WGS 84\", \"datum_ensemble\": {\"name\": \"World Geodetic System 1984 ensemble\", \"members\": [{\"name\": \"World Geodetic System 1984 (Transit)\"}, {\"name\": \"World Geodetic System 1984 (G730)\"}, {\"name\": \"World Geodetic System 1984 (G873)\"}, {\"name\": \"World Geodetic System 1984 (G1150)\"}, {\"name\": \"World Geodetic System 1984 (G1674)\"}, {\"name\": \"World Geodetic System 1984 (G1762)\"}, {\"name\": \"World Geodetic System 1984 (G2139)\"}, {\"name\": \"World Geodetic System 1984 (G2296)\"}], \"ellipsoid\": {\"name\": \"WGS 84\", \"semi_major_axis\": 6378137, \"inverse_flattening\": 298.257223563}, \"accuracy\": \"2.0\", \"id\": {\"authority\": \"EPSG\", \"code\": 6326}}, \"coordinate_system\": {\"subtype\": \"ellipsoidal\", \"axis\": [{\"name\": \"Geodetic latitude\", \"abbreviation\": \"Lat\", \"direction\": \"north\", \"unit\": \"degree\"}, {\"name\": \"Geodetic longitude\", \"abbreviation\": \"Lon\", \"direction\": \"east\", \"unit\": \"degree\"}]}, \"scope\": \"Horizontal component of 3D system.\", \"area\": \"World.\", \"bbox\": {\"south_latitude\": -90, \"west_longitude\": -180, \"north_latitude\": 90, \"east_longitude\": 180}, \"id\": {\"authority\": \"EPSG\", \"code\": 4326}}",
        "columns": [
          "osmid",
          "name",
          "highway",
          "cycleway",
          "bicycle",
          "surface",
          "segregated",
          "geometry",
          "length_m",
          "category"
        ],
        "memory_usage_mb": 36.83
      },
      "geometry_analysis": {
        "geometry_types": {
          "MultiLineString": 124329,
          "GeometryCollection": 16,
          "LineString": 5,
          "Point": 1
        },
        "invalid_geometries": 0,
        "empty_geometries": 0,
        "null_geometries": 0,
        "topology_issues": []
      },
      "attribute_analysis": {
        "total_columns": 9,
        "null_analysis": {
          "osmid": {
            "null_count": 0,
            "null_percentage": 0.0
          },
          "name": {
            "null_count": 76301,
            "null_percentage": 61.4
          },
          "highway": {
            "null_count": 16,
            "null_percentage": 0.0
          },
          "cycleway": {
            "null_count": 123681,
            "null_percentage": 99.5
          },
          "bicycle": {
            "null_count": 110351,
            "null_percentage": 88.7
          },
          "surface": {
            "null_count": 32340,
            "null_percentage": 26.0
          },
          "segregated": {
            "null_count": 120243,
            "null_percentage": 96.7
          },
          "length_m": {
            "null_count": 0,
            "null_percentage": 0.0
          },
          "category": {
            "null_count": 0,
            "null_percentage": 0.0
          }
        },
        "data_types": {
          "osmid": "int64",
          "name": "object",
          "highway": "object",
          "cycleway": "object",
          "bicycle": "object",
          "surface": "object",
          "segregated": "object",
          "length_m": "float64",
          "category": "object"
        },
        "unique_values": {}
      },
      "spatial_analysis": {
        "bounding_box": [
          9.0,
          48.599998474121094,
          9.399999618530273,
          48.900001525878906
        ],
        "extent_analysis": {
          "within_stuttgart": false
        },
        "density_analysis": {
          "features_per_km2": 84.11
        },
        "size_analysis": {
          "lines": {
            "count": 124334,
            "min_length_m": 1.0046822266327389,
            "max_length_m": 5657.3650179396345,
            "mean_length_m": 119.20340072516032,
            "tiny_features": 0
          }
        }
      }
    },
    "pt_stops": {
      "layer_name": "pt_stops",
      "total_features": 92224,
      "status": "GOOD",
      "issues": [],
      "warnings": [],
      "recommendations": [],
      "statistics": {
        "feature_count": 92224,
        "crs": "{\"$schema\": \"https://proj.org/schemas/v0.7/projjson.schema.json\", \"type\": \"GeographicCRS\", \"name\": \"WGS 84\", \"datum_ensemble\": {\"name\": \"World Geodetic System 1984 ensemble\", \"members\": [{\"name\": \"World Geodetic System 1984 (Transit)\"}, {\"name\": \"World Geodetic System 1984 (G730)\"}, {\"name\": \"World Geodetic System 1984 (G873)\"}, {\"name\": \"World Geodetic System 1984 (G1150)\"}, {\"name\": \"World Geodetic System 1984 (G1674)\"}, {\"name\": \"World Geodetic System 1984 (G1762)\"}, {\"name\": \"World Geodetic System 1984 (G2139)\"}, {\"name\": \"World Geodetic System 1984 (G2296)\"}], \"ellipsoid\": {\"name\": \"WGS 84\", \"semi_major_axis\": 6378137, \"inverse_flattening\": 298.257223563}, \"accuracy\": \"2.0\", \"id\": {\"authority\": \"EPSG\", \"code\": 6326}}, \"coordinate_system\": {\"subtype\": \"ellipsoidal\", \"axis\": [{\"name\": \"Geodetic latitude\", \"abbreviation\": \"Lat\", \"direction\": \"north\", \"unit\": \"degree\"}, {\"name\": \"Geodetic longitude\", \"abbreviation\": \"Lon\", \"direction\": \"east\", \"unit\": \"degree\"}]}, \"scope\": \"Horizontal component of 3D system.\", \"area\": \"World.\", \"bbox\": {\"south_latitude\": -90, \"west_longitude\": -180, \"north_latitude\": 90, \"east_longitude\": 180}, \"id\": {\"authority\": \"EPSG\", \"code\": 4326}}",
        "columns": [
          "osmid",
          "name",
          "railway",
          "public_transport",
          "highway",
          "amenity",
          "aeroway",
          "aerialway",
          "operator",
          "ref",
          "geometry",
          "category"
        ],
        "memory_usage_mb": 31.05
      },
      "geometry_analysis": {
        "geometry_types": {
          "Point": 64801,
          "Polygon": 19771,
          "MultiLineString": 5555,
          "LineString": 1843,
          "MultiPolygon": 247,
          "GeometryCollection": 7
        },
        "invalid_geometries": 0,
        "empty_geometries": 0,
        "null_geometries": 0,
        "topology_issues": []
      },
      "attribute_analysis": {
        "total_columns": 11,
        "null_analysis": {
          "osmid": {
            "null_count": 0,
            "null_percentage": 0.0
          },
          "name": {
            "null_count": 70480,
            "null_percentage": 76.4
          },
          "railway": {
            "null_count": 72565,
            "null_percentage": 78.7
          },
          "public_transport": {
            "null_count": 84524,
            "null_percentage": 91.7
          },
          "highway": {
            "null_count": 92178,
            "null_percentage": 100.0
          },
          "amenity": {
            "null_count": 30238,
            "null_percentage": 32.8
          },
          "aeroway": {
            "null_count": 88268,
            "null_percentage": 95.7
          },
          "aerialway": {
            "null_count": 92202,
            "null_percentage": 100.0
          },
          "operator": {
            "null_count": 75428,
            "null_percentage": 81.8
          },
          "ref": {
            "null_count": 84477,
            "null_percentage": 91.6
          },
          "category": {
            "null_count": 0,
            "null_percentage": 0.0
          }
        },
        "data_types": {
          "osmid": "int64",
          "name": "object",
          "railway": "object",
          "public_transport": "object",
          "highway": "object",
          "amenity": "object",
          "aeroway": "object",
          "aerialway": "object",
          "operator": "object",
          "ref": "object",
          "category": "object"
        },
        "unique_values": {}
      },
      "spatial_analysis": {
        "bounding_box": [
          9.000000953674316,
          48.60000228881836,
          9.399999618530273,
          48.900001525878906
        ],
        "extent_analysis": {
          "within_stuttgart": false
        },
        "density_analysis": {
          "features_per_km2": 62.38
        },
        "size_analysis": {
          "polygons": {
            "count": 20018,
            "min_area_m2": 1.00957511644727,
            "max_area_m2": 1547826.4721034216,
            "mean_area_m2": 1166.2713776854982,
            "tiny_features": 0
          },
          "lines": {
            "count": 7398,
            "min_length_m": 1.0162645820880216,
            "max_length_m": 12511.858753819739,
            "mean_length_m": 218.14100482654842,
            "tiny_features": 0
          }
        }
      }
    },
    "boundaries": {
      "layer_name": "boundaries",
      "total_features": 360,
      "status": "GOOD",
      "issues": [],
      "warnings": [],
      "recommendations": [],
      "statistics": {
        "feature_count": 360,
        "crs": "{\"$schema\": \"https://proj.org/schemas/v0.7/projjson.schema.json\", \"type\": \"GeographicCRS\", \"name\": \"WGS 84\", \"datum_ensemble\": {\"name\": \"World Geodetic System 1984 ensemble\", \"members\": [{\"name\": \"World Geodetic System 1984 (Transit)\"}, {\"name\": \"World Geodetic System 1984 (G730)\"}, {\"name\": \"World Geodetic System 1984 (G873)\"}, {\"name\": \"World Geodetic System 1984 (G1150)\"}, {\"name\": \"World Geodetic System 1984 (G1674)\"}, {\"name\": \"World Geodetic System 1984 (G1762)\"}, {\"name\": \"World Geodetic System 1984 (G2139)\"}, {\"name\": \"World Geodetic System 1984 (G2296)\"}], \"ellipsoid\": {\"name\": \"WGS 84\", \"semi_major_axis\": 6378137, \"inverse_flattening\": 298.257223563}, \"accuracy\": \"2.0\", \"id\": {\"authority\": \"EPSG\", \"code\": 6326}}, \"coordinate_system\": {\"subtype\": \"ellipsoidal\", \"axis\": [{\"name\": \"Geodetic latitude\", \"abbreviation\": \"Lat\", \"direction\": \"north\", \"unit\": \"degree\"}, {\"name\": \"Geodetic longitude\", \"abbreviation\": \"Lon\", \"direction\": \"east\", \"unit\": \"degree\"}]}, \"scope\": \"Horizontal component of 3D system.\", \"area\": \"World.\", \"bbox\": {\"south_latitude\": -90, \"west_longitude\": -180, \"north_latitude\": 90, \"east_longitude\": 180}, \"id\": {\"authority\": \"EPSG\", \"code\": 4326}}",
        "columns": [
          "osmid",
          "name",
          "admin_level",
          "boundary",
          "geometry",
          "category"
        ],
        "memory_usage_mb": 0.09
      },
      "geometry_analysis": {
        "geometry_types": {
          "Polygon": 329,
          "MultiPolygon": 31
        },
        "invalid_geometries": 0,
        "empty_geometries": 0,
        "null_geometries": 0,
        "topology_issues": []
      },
      "attribute_analysis": {
        "total_columns": 5,
        "null_analysis": {
          "osmid": {
            "null_count": 0,
            "null_percentage": 0.0
          },
          "name": {
            "null_count": 0,
            "null_percentage": 0.0
          },
          "admin_level": {
            "null_count": 8,
            "null_percentage": 2.2
          },
          "boundary": {
            "null_count": 0,
            "null_percentage": 0.0
          },
          "category": {
            "null_count": 0,
            "null_percentage": 0.0
          }
        },
        "data_types": {
          "osmid": "int64",
          "name": "object",
          "admin_level": "object",
          "boundary": "object",
          "category": "object"
        },
        "unique_values": {
          "osmid": 360,
          "name": 338,
          "admin_level": 6,
          "boundary": 1,
          "category": 1
        }
      },
      "spatial_analysis": {
        "bounding_box": [
          9.0,
          48.599998474121094,
          9.399999618530273,
          48.89998245239258
        ],
        "extent_analysis": {
          "within_stuttgart": false
        },
        "density_analysis": {
          "features_per_km2": 0.24
        },
        "size_analysis": {
          "polygons": {
            "count": 360,
            "min_area_m2": 24.970173542371235,
            "max_area_m2": 207159875.37808043,
            "mean_area_m2": 6551589.303874851,
            "tiny_features": 0
          }
        }
      }
    },
    "amenities": {
      "layer_name": "amenities",
      "total_features": 61888,
      "status": "GOOD",
      "issues": [],
      "warnings": [],
      "recommendations": [],
      "statistics": {
        "feature_count": 61888,
        "crs": "{\"$schema\": \"https://proj.org/schemas/v0.7/projjson.schema.json\", \"type\": \"GeographicCRS\", \"name\": \"WGS 84\", \"datum_ensemble\": {\"name\": \"World Geodetic System 1984 ensemble\", \"members\": [{\"name\": \"World Geodetic System 1984 (Transit)\"}, {\"name\": \"World Geodetic System 1984 (G730)\"}, {\"name\": \"World Geodetic System 1984 (G873)\"}, {\"name\": \"World Geodetic System 1984 (G1150)\"}, {\"name\": \"World Geodetic System 1984 (G1674)\"}, {\"name\": \"World Geodetic System 1984 (G1762)\"}, {\"name\": \"World Geodetic System 1984 (G2139)\"}, {\"name\": \"World Geodetic System 1984 (G2296)\"}], \"ellipsoid\": {\"name\": \"WGS 84\", \"semi_major_axis\": 6378137, \"inverse_flattening\": 298.257223563}, \"accuracy\": \"2.0\", \"id\": {\"authority\": \"EPSG\", \"code\": 6326}}, \"coordinate_system\": {\"subtype\": \"ellipsoidal\", \"axis\": [{\"name\": \"Geodetic latitude\", \"abbreviation\": \"Lat\", \"direction\": \"north\", \"unit\": \"degree\"}, {\"name\": \"Geodetic longitude\", \"abbreviation\": \"Lon\", \"direction\": \"east\", \"unit\": \"degree\"}]}, \"scope\": \"Horizontal component of 3D system.\", \"area\": \"World.\", \"bbox\": {\"south_latitude\": -90, \"west_longitude\": -180, \"north_latitude\": 90, \"east_longitude\": 180}, \"id\": {\"authority\": \"EPSG\", \"code\": 4326}}",
        "columns": [
          "osmid",
          "name",
          "amenity",
          "operator",
          "opening_hours",
          "geometry",
          "category"
        ],
        "memory_usage_mb": 13.79
      },
      "geometry_analysis": {
        "geometry_types": {
          "Point": 42320,
          "Polygon": 19523,
          "MultiPolygon": 39,
          "GeometryCollection": 3,
          "LineString": 3
        },
        "invalid_geometries": 0,
        "empty_geometries": 0,
        "null_geometries": 0,
        "topology_issues": []
      },
      "attribute_analysis": {
        "total_columns": 6,
        "null_analysis": {
          "osmid": {
            "null_count": 0,
            "null_percentage": 0.0
          },
          "name": {
            "null_count": 48781,
            "null_percentage": 78.8
          },
          "amenity": {
            "null_count": 0,
            "null_percentage": 0.0
          },
          "operator": {
            "null_count": 55039,
            "null_percentage": 88.9
          },
          "opening_hours": {
            "null_count": 55548,
            "null_percentage": 89.8
          },
          "category": {
            "null_count": 0,
            "null_percentage": 0.0
          }
        },
        "data_types": {
          "osmid": "int64",
          "name": "object",
          "amenity": "object",
          "operator": "object",
          "opening_hours": "object",
          "category": "object"
        },
        "unique_values": {}
      },
      "spatial_analysis": {
        "bounding_box": [
          9.000000953674316,
          48.60000228881836,
          9.399984359741211,
          48.900001525878906
        ],
        "extent_analysis": {
          "within_stuttgart": false
        },
        "density_analysis": {
          "features_per_km2": 41.86
        },
        "size_analysis": {
          "polygons": {
            "count": 19562,
            "min_area_m2": 1.00957511644727,
            "max_area_m2": 608755.4739914422,
            "mean_area_m2": 1028.264540624109,
            "tiny_features": 0
          },
          "lines": {
            "count": 3,
            "min_length_m": 5.463560218288584,
            "max_length_m": 26.848428603001114,
            "mean_length_m": 18.278733717728887,
            "tiny_features": 0
          }
        }
      }
    }
  },
  "validation_results": {
    "timestamp": "2025-08-14T10:56:06.069648",
    "config": {
      "expected_crs": "EPSG:4326",
      "analytics_crs": "EPSG:25832",
      "layer_configs": {
        "roads": {
          "expected_geom_types": [
            "LineString",
            "MultiLineString"
          ],
          "required_columns": [
            "osmid",
            "highway"
          ]
        },
        "buildings": {
          "expected_geom_types": [
            "Polygon",
            "MultiPolygon"
          ],
          "required_columns": [
            "osmid",
            "building"
          ]
        },
        "landuse": {
          "expected_geom_types": [
            "Polygon",
            "MultiPolygon"
          ],
          "required_columns": [
            "osmid"
          ]
        },
        "amenities": {
          "expected_geom_types": [
            "Point",
            "Polygon",
            "MultiPolygon"
          ],
          "required_columns": [
            "osmid",
            "amenity"
          ]
        }
      }
    },
    "summary": {
      "total_layers": 12,
      "passed_layers": 9,
      "failed_layers": 3,
      "total_features": 926498
    },
    "layers": {
      "amenities": {
        "layer_name": "amenities",
        "total_features": 61888,
        "passed_checks": 7,
        "failed_checks": 1,
        "warnings": [
          "Unexpected geometry types: ['LineString', 'GeometryCollection']",
          "Column 'name' has 78.8% null values",
          "Column 'operator' has 88.9% null values",
          "Column 'opening_hours' has 89.8% null values"
        ],
        "success_rate": 87.5,
        "is_valid": true,
        "errors": [],
        "details": {
          "total_features": 61888,
          "crs": {
            "valid": true,
            "errors": [],
            "crs": "EPSG:4326"
          },
          "geometry": {
            "passed": 2,
            "failed": 1,
            "errors": [],
            "warnings": [
              "Unexpected geometry types: ['LineString', 'GeometryCollection']"
            ],
            "invalid_geometries": 0,
            "geometry_types": {
              "Point": 42320,
              "Polygon": 19523,
              "MultiPolygon": 39,
              "GeometryCollection": 3,
              "LineString": 3
            },
            "topology_errors": []
          },
          "attributes": {
            "passed": 1,
            "failed": 0,
            "warnings": [
              "Column 'name' has 78.8% null values",
              "Column 'operator' has 88.9% null values",
              "Column 'opening_hours' has 89.8% null values"
            ],
            "missing_columns": [],
            "null_counts": {
              "osmid": {
                "count": 0,
                "percentage": 0.0
              },
              "name": {
                "count": 48781,
                "percentage": 78.82
              },
              "amenity": {
                "count": 0,
                "percentage": 0.0
              },
              "operator": {
                "count": 55039,
                "percentage": 88.93
              },
              "opening_hours": {
                "count": 55548,
                "percentage": 89.76
              },
              "category": {
                "count": 0,
                "percentage": 0.0
              }
            },
            "column_types": {
              "osmid": "int64",
              "name": "object",
              "amenity": "object",
              "operator": "object",
              "opening_hours": "object",
              "category": "object"
            }
          },
          "spatial_extent": {
            "valid": true,
            "warnings": [],
            "actual_bbox": [
              9.000000953674316,
              48.60000228881836,
              9.399984359741211,
              48.900001525878906
            ],
            "expected_bbox": null
          },
          "duplicates": {
            "duplicates": 0,
            "warnings": [],
            "duplicate_types": {
              "geometry": 0,
              "osmid": 0
            }
          },
          "feature_sizes": {
            "passed": 1,
            "failed": 0,
            "warnings": [],
            "size_stats": {
              "polygons": {
                "count": 19562,
                "min_area_m2": 1.00957511644727,
                "max_area_m2": 608755.4739914422,
                "mean_area_m2": 1028.264540624109,
                "tiny_features": 0
              },
              "lines": {
                "count": 3,
                "min_length_m": 5.463560218288584,
                "max_length_m": 26.848428603001114,
                "mean_length_m": 18.278733717728887,
                "tiny_features": 0
              }
            }
          }
        }
      },
      "boundaries": {
        "layer_name": "boundaries",
        "total_features": 360,
        "passed_checks": 6,
        "failed_checks": 0,
        "warnings": [],
        "success_rate": 100.0,
        "is_valid": true,
        "errors": [],
        "details": {
          "total_features": 360,
          "crs": {
            "valid": true,
            "errors": [],
            "crs": "EPSG:4326"
          },
          "geometry": {
            "passed": 2,
            "failed": 0,
            "errors": [],
            "warnings": [],
            "invalid_geometries": 0,
            "geometry_types": {
              "Polygon": 329,
              "MultiPolygon": 31
            },
            "topology_errors": []
          },
          "attributes": {
            "passed": 0,
            "failed": 0,
            "warnings": [],
            "missing_columns": [],
            "null_counts": {
              "osmid": {
                "count": 0,
                "percentage": 0.0
              },
              "name": {
                "count": 0,
                "percentage": 0.0
              },
              "admin_level": {
                "count": 8,
                "percentage": 2.22
              },
              "boundary": {
                "count": 0,
                "percentage": 0.0
              },
              "category": {
                "count": 0,
                "percentage": 0.0
              }
            },
            "column_types": {
              "osmid": "int64",
              "name": "object",
              "admin_level": "object",
              "boundary": "object",
              "category": "object"
            }
          },
          "spatial_extent": {
            "valid": true,
            "warnings": [],
            "actual_bbox": [
              9.0,
              48.599998474121094,
              9.399999618530273,
              48.89998245239258
            ],
            "expected_bbox": null
          },
          "duplicates": {
            "duplicates": 0,
            "warnings": [],
            "duplicate_types": {
              "geometry": 0,
              "osmid": 0
            }
          },
          "feature_sizes": {
            "passed": 1,
            "failed": 0,
            "warnings": [],
            "size_stats": {
              "polygons": {
                "count": 360,
                "min_area_m2": 24.970173542371235,
                "max_area_m2": 207159875.37808043,
                "mean_area_m2": 6551589.303874851,
                "tiny_features": 0
              }
            }
          }
        }
      },
      "buildings": {
        "layer_name": "buildings",
        "total_features": 379611,
        "passed_checks": 6,
        "failed_checks": 2,
        "warnings": [
          "Unexpected geometry types: ['LineString', 'MultiLineString', 'GeometryCollection']",
          "Column 'name' has 97.5% null values",
          "Column 'levels' has 100.0% null values",
          "Column 'height' has 99.7% null values",
          "Found 9 lines shorter than 1.0 m"
        ],
        "success_rate": 75.0,
        "is_valid": true,
        "errors": [],
        "details": {
          "total_features": 379611,
          "crs": {
            "valid": true,
            "errors": [],
            "crs": "EPSG:4326"
          },
          "geometry": {
            "passed": 2,
            "failed": 1,
            "errors": [],
            "warnings": [
              "Unexpected geometry types: ['LineString', 'MultiLineString', 'GeometryCollection']"
            ],
            "invalid_geometries": 0,
            "geometry_types": {
              "Polygon": 379396,
              "MultiPolygon": 84,
              "LineString": 66,
              "GeometryCollection": 56,
              "MultiLineString": 9
            },
            "topology_errors": []
          },
          "attributes": {
            "passed": 1,
            "failed": 0,
            "warnings": [
              "Column 'name' has 97.5% null values",
              "Column 'levels' has 100.0% null values",
              "Column 'height' has 99.7% null values"
            ],
            "missing_columns": [],
            "null_counts": {
              "osmid": {
                "count": 0,
                "percentage": 0.0
              },
              "name": {
                "count": 370007,
                "percentage": 97.47
              },
              "building": {
                "count": 0,
                "percentage": 0.0
              },
              "levels": {
                "count": 379609,
                "percentage": 100.0
              },
              "height": {
                "count": 378446,
                "percentage": 99.69
              },
              "area_m2": {
                "count": 0,
                "percentage": 0.0
              },
              "category": {
                "count": 0,
                "percentage": 0.0
              }
            },
            "column_types": {
              "osmid": "int64",
              "name": "object",
              "building": "object",
              "levels": "object",
              "height": "object",
              "area_m2": "float64",
              "category": "object"
            }
          },
          "spatial_extent": {
            "valid": true,
            "warnings": [],
            "actual_bbox": [
              9.0,
              48.60000228881836,
              9.399999618530273,
              48.900001525878906
            ],
            "expected_bbox": null
          },
          "duplicates": {
            "duplicates": 0,
            "warnings": [],
            "duplicate_types": {
              "geometry": 0,
              "osmid": 0
            }
          },
          "feature_sizes": {
            "passed": 0,
            "failed": 1,
            "warnings": [
              "Found 9 lines shorter than 1.0 m"
            ],
            "size_stats": {
              "polygons": {
                "count": 379480,
                "min_area_m2": 1.0080397933994367,
                "max_area_m2": 76170.63381906677,
                "mean_area_m2": 177.10274977787762,
                "tiny_features": 0
              },
              "lines": {
                "count": 75,
                "min_length_m": 0.1399765059194992,
                "max_length_m": 26.659231979477326,
                "mean_length_m": 8.171515424013924,
                "tiny_features": 9
              }
            }
          }
        }
      },
      "cycle": {
        "layer_name": "cycle",
        "total_features": 124351,
        "passed_checks": 6,
        "failed_checks": 0,
        "warnings": [
          "Column 'name' has 61.4% null values",
          "Column 'cycleway' has 99.5% null values",
          "Column 'bicycle' has 88.7% null values",
          "Column 'segregated' has 96.7% null values"
        ],
        "success_rate": 100.0,
        "is_valid": true,
        "errors": [],
        "details": {
          "total_features": 124351,
          "crs": {
            "valid": true,
            "errors": [],
            "crs": "EPSG:4326"
          },
          "geometry": {
            "passed": 2,
            "failed": 0,
            "errors": [],
            "warnings": [],
            "invalid_geometries": 0,
            "geometry_types": {
              "MultiLineString": 124329,
              "GeometryCollection": 16,
              "LineString": 5,
              "Point": 1
            },
            "topology_errors": []
          },
          "attributes": {
            "passed": 0,
            "failed": 0,
            "warnings": [
              "Column 'name' has 61.4% null values",
              "Column 'cycleway' has 99.5% null values",
              "Column 'bicycle' has 88.7% null values",
              "Column 'segregated' has 96.7% null values"
            ],
            "missing_columns": [],
            "null_counts": {
              "osmid": {
                "count": 0,
                "percentage": 0.0
              },
              "name": {
                "count": 76301,
                "percentage": 61.36
              },
              "highway": {
                "count": 16,
                "percentage": 0.01
              },
              "cycleway": {
                "count": 123681,
                "percentage": 99.46
              },
              "bicycle": {
                "count": 110351,
                "percentage": 88.74
              },
              "surface": {
                "count": 32340,
                "percentage": 26.01
              },
              "segregated": {
                "count": 120243,
                "percentage": 96.7
              },
              "length_m": {
                "count": 0,
                "percentage": 0.0
              },
              "category": {
                "count": 0,
                "percentage": 0.0
              }
            },
            "column_types": {
              "osmid": "int64",
              "name": "object",
              "highway": "object",
              "cycleway": "object",
              "bicycle": "object",
              "surface": "object",
              "segregated": "object",
              "length_m": "float64",
              "category": "object"
            }
          },
          "spatial_extent": {
            "valid": true,
            "warnings": [],
            "actual_bbox": [
              9.0,
              48.599998474121094,
              9.399999618530273,
              48.900001525878906
            ],
            "expected_bbox": null
          },
          "duplicates": {
            "duplicates": 0,
            "warnings": [],
            "duplicate_types": {
              "geometry": 0,
              "osmid": 0
            }
          },
          "feature_sizes": {
            "passed": 1,
            "failed": 0,
            "warnings": [],
            "size_stats": {
              "lines": {
                "count": 124334,
                "min_length_m": 1.0046822266327389,
                "max_length_m": 5657.3650179396345,
                "mean_length_m": 119.20340072516032,
                "tiny_features": 0
              }
            }
          }
        }
      },
      "landuse": {
        "layer_name": "landuse",
        "total_features": 30772,
        "passed_checks": 7,
        "failed_checks": 1,
        "warnings": [
          "Unexpected geometry types: ['LineString', 'MultiLineString', 'GeometryCollection']",
          "Column 'natural' has 84.9% null values"
        ],
        "success_rate": 87.5,
        "is_valid": true,
        "errors": [],
        "details": {
          "total_features": 30772,
          "crs": {
            "valid": true,
            "errors": [],
            "crs": "EPSG:4326"
          },
          "geometry": {
            "passed": 2,
            "failed": 1,
            "errors": [],
            "warnings": [
              "Unexpected geometry types: ['LineString', 'MultiLineString', 'GeometryCollection']"
            ],
            "invalid_geometries": 0,
            "geometry_types": {
              "Polygon": 30509,
              "MultiPolygon": 243,
              "LineString": 18,
              "GeometryCollection": 1,
              "MultiLineString": 1
            },
            "topology_errors": []
          },
          "attributes": {
            "passed": 1,
            "failed": 0,
            "warnings": [
              "Column 'natural' has 84.9% null values"
            ],
            "missing_columns": [],
            "null_counts": {
              "osmid": {
                "count": 0,
                "percentage": 0.0
              },
              "landuse": {
                "count": 4637,
                "percentage": 15.07
              },
              "natural": {
                "count": 26135,
                "percentage": 84.93
              },
              "area_m2": {
                "count": 0,
                "percentage": 0.0
              },
              "category": {
                "count": 0,
                "percentage": 0.0
              }
            },
            "column_types": {
              "osmid": "int64",
              "landuse": "object",
              "natural": "object",
              "area_m2": "float64",
              "category": "object"
            }
          },
          "spatial_extent": {
            "valid": true,
            "warnings": [],
            "actual_bbox": [
              9.0,
              48.599998474121094,
              9.39999771118164,
              48.900001525878906
            ],
            "expected_bbox": null
          },
          "duplicates": {
            "duplicates": 0,
            "warnings": [],
            "duplicate_types": {
              "geometry": 0,
              "osmid": 0
            }
          },
          "feature_sizes": {
            "passed": 1,
            "failed": 0,
            "warnings": [],
            "size_stats": {
              "polygons": {
                "count": 30752,
                "min_area_m2": 1.41428178493827,
                "max_area_m2": 25598065.93569422,
                "mean_area_m2": 28616.11385310535,
                "tiny_features": 0
              },
              "lines": {
                "count": 19,
                "min_length_m": 8.074360550178888,
                "max_length_m": 111.5466062278976,
                "mean_length_m": 37.376944518765235,
                "tiny_features": 0
              }
            }
          }
        }
      },
      "pt_stops": {
        "layer_name": "pt_stops",
        "total_features": 92224,
        "passed_checks": 6,
        "failed_checks": 0,
        "warnings": [
          "Column 'name' has 76.4% null values",
          "Column 'railway' has 78.7% null values",
          "Column 'public_transport' has 91.7% null values",
          "Column 'highway' has 100.0% null values",
          "Column 'aeroway' has 95.7% null values",
          "Column 'aerialway' has 100.0% null values",
          "Column 'operator' has 81.8% null values",
          "Column 'ref' has 91.6% null values"
        ],
        "success_rate": 100.0,
        "is_valid": true,
        "errors": [],
        "details": {
          "total_features": 92224,
          "crs": {
            "valid": true,
            "errors": [],
            "crs": "EPSG:4326"
          },
          "geometry": {
            "passed": 2,
            "failed": 0,
            "errors": [],
            "warnings": [],
            "invalid_geometries": 0,
            "geometry_types": {
              "Point": 64801,
              "Polygon": 19771,
              "MultiLineString": 5555,
              "LineString": 1843,
              "MultiPolygon": 247,
              "GeometryCollection": 7
            },
            "topology_errors": []
          },
          "attributes": {
            "passed": 0,
            "failed": 0,
            "warnings": [
              "Column 'name' has 76.4% null values",
              "Column 'railway' has 78.7% null values",
              "Column 'public_transport' has 91.7% null values",
              "Column 'highway' has 100.0% null values",
              "Column 'aeroway' has 95.7% null values",
              "Column 'aerialway' has 100.0% null values",
              "Column 'operator' has 81.8% null values",
              "Column 'ref' has 91.6% null values"
            ],
            "missing_columns": [],
            "null_counts": {
              "osmid": {
                "count": 0,
                "percentage": 0.0
              },
              "name": {
                "count": 70480,
                "percentage": 76.42
              },
              "railway": {
                "count": 72565,
                "percentage": 78.68
              },
              "public_transport": {
                "count": 84524,
                "percentage": 91.65
              },
              "highway": {
                "count": 92178,
                "percentage": 99.95
              },
              "amenity": {
                "count": 30238,
                "percentage": 32.79
              },
              "aeroway": {
                "count": 88268,
                "percentage": 95.71
              },
              "aerialway": {
                "count": 92202,
                "percentage": 99.98
              },
              "operator": {
                "count": 75428,
                "percentage": 81.79
              },
              "ref": {
                "count": 84477,
                "percentage": 91.6
              },
              "category": {
                "count": 0,
                "percentage": 0.0
              }
            },
            "column_types": {
              "osmid": "int64",
              "name": "object",
              "railway": "object",
              "public_transport": "object",
              "highway": "object",
              "amenity": "object",
              "aeroway": "object",
              "aerialway": "object",
              "operator": "object",
              "ref": "object",
              "category": "object"
            }
          },
          "spatial_extent": {
            "valid": true,
            "warnings": [],
            "actual_bbox": [
              9.000000953674316,
              48.60000228881836,
              9.399999618530273,
              48.900001525878906
            ],
            "expected_bbox": null
          },
          "duplicates": {
            "duplicates": 0,
            "warnings": [],
            "duplicate_types": {
              "geometry": 0,
              "osmid": 0
            }
          },
          "feature_sizes": {
            "passed": 1,
            "failed": 0,
            "warnings": [],
            "size_stats": {
              "polygons": {
                "count": 20018,
                "min_area_m2": 1.00957511644727,
                "max_area_m2": 1547826.4721034216,
                "mean_area_m2": 1166.2713776854982,
                "tiny_features": 0
              },
              "lines": {
                "count": 7398,
                "min_length_m": 1.0162645820880216,
                "max_length_m": 12511.858753819739,
                "mean_length_m": 218.14100482654842,
                "tiny_features": 0
              }
            }
          }
        }
      },
      "roads": {
        "layer_name": "roads",
        "total_features": 86085,
        "passed_checks": 7,
        "failed_checks": 1,
        "warnings": [
          "Unexpected geometry types: ['GeometryCollection']",
          "Column 'maxspeed' has 53.2% null values",
          "Column 'lanes' has 78.4% null values",
          "Column 'oneway' has 81.0% null values",
          "Column 'bridge' has 98.5% null values",
          "Column 'tunnel' has 99.2% null values",
          "Column 'access' has 90.2% null values"
        ],
        "success_rate": 87.5,
        "is_valid": true,
        "errors": [],
        "details": {
          "total_features": 86085,
          "crs": {
            "valid": true,
            "errors": [],
            "crs": "EPSG:4326"
          },
          "geometry": {
            "passed": 2,
            "failed": 1,
            "errors": [],
            "warnings": [
              "Unexpected geometry types: ['GeometryCollection']"
            ],
            "invalid_geometries": 0,
            "geometry_types": {
              "MultiLineString": 86077,
              "GeometryCollection": 8
            },
            "topology_errors": []
          },
          "attributes": {
            "passed": 1,
            "failed": 0,
            "warnings": [
              "Column 'maxspeed' has 53.2% null values",
              "Column 'lanes' has 78.4% null values",
              "Column 'oneway' has 81.0% null values",
              "Column 'bridge' has 98.5% null values",
              "Column 'tunnel' has 99.2% null values",
              "Column 'access' has 90.2% null values"
            ],
            "missing_columns": [],
            "null_counts": {
              "osmid": {
                "count": 0,
                "percentage": 0.0
              },
              "name": {
                "count": 41914,
                "percentage": 48.69
              },
              "highway": {
                "count": 0,
                "percentage": 0.0
              },
              "maxspeed": {
                "count": 45763,
                "percentage": 53.16
              },
              "lanes": {
                "count": 67529,
                "percentage": 78.44
              },
              "surface": {
                "count": 22425,
                "percentage": 26.05
              },
              "oneway": {
                "count": 69752,
                "percentage": 81.03
              },
              "bridge": {
                "count": 84823,
                "percentage": 98.53
              },
              "tunnel": {
                "count": 85378,
                "percentage": 99.18
              },
              "access": {
                "count": 77678,
                "percentage": 90.23
              },
              "length_m": {
                "count": 0,
                "percentage": 0.0
              },
              "category": {
                "count": 0,
                "percentage": 0.0
              }
            },
            "column_types": {
              "osmid": "int64",
              "name": "object",
              "highway": "object",
              "maxspeed": "object",
              "lanes": "object",
              "surface": "object",
              "oneway": "object",
              "bridge": "object",
              "tunnel": "object",
              "access": "object",
              "length_m": "float64",
              "category": "object"
            }
          },
          "spatial_extent": {
            "valid": true,
            "warnings": [],
            "actual_bbox": [
              9.0,
              48.599998474121094,
              9.399999618530273,
              48.900001525878906
            ],
            "expected_bbox": null
          },
          "duplicates": {
            "duplicates": 0,
            "warnings": [],
            "duplicate_types": {
              "geometry": 0,
              "osmid": 0
            }
          },
          "feature_sizes": {
            "passed": 1,
            "failed": 0,
            "warnings": [],
            "size_stats": {
              "lines": {
                "count": 86077,
                "min_length_m": 1.0046822266327389,
                "max_length_m": 5657.3650179396345,
                "mean_length_m": 107.74907996473073,
                "tiny_features": 0
              }
            }
          }
        }
      },
      "test_boundaries": {
        "layer_name": "test_boundaries",
        "total_features": 162,
        "passed_checks": 5,
        "failed_checks": 1,
        "warnings": [
          "Found 7 duplicate features"
        ],
        "success_rate": 83.33,
        "is_valid": true,
        "errors": [],
        "details": {
          "total_features": 162,
          "crs": {
            "valid": true,
            "errors": [],
            "crs": "EPSG:4326"
          },
          "geometry": {
            "passed": 2,
            "failed": 0,
            "errors": [],
            "warnings": [],
            "invalid_geometries": 0,
            "geometry_types": {
              "Polygon": 150,
              "MultiPolygon": 12
            },
            "topology_errors": []
          },
          "attributes": {
            "passed": 0,
            "failed": 0,
            "warnings": [],
            "missing_columns": [],
            "null_counts": {
              "osmid": {
                "count": 0,
                "percentage": 0.0
              },
              "name": {
                "count": 0,
                "percentage": 0.0
              },
              "admin_level": {
                "count": 7,
                "percentage": 4.32
              },
              "boundary": {
                "count": 0,
                "percentage": 0.0
              },
              "category": {
                "count": 0,
                "percentage": 0.0
              }
            },
            "column_types": {
              "osmid": "int64",
              "name": "object",
              "admin_level": "object",
              "boundary": "object",
              "category": "object"
            }
          },
          "spatial_extent": {
            "valid": true,
            "warnings": [],
            "actual_bbox": [
              9.100071907043457,
              48.70002365112305,
              9.299994468688965,
              48.79996109008789
            ],
            "expected_bbox": null
          },
          "duplicates": {
            "duplicates": 7,
            "warnings": [
              "Found 7 duplicate features"
            ],
            "duplicate_types": {
              "geometry": 7,
              "osmid": 0
            }
          },
          "feature_sizes": {
            "passed": 1,
            "failed": 0,
            "warnings": [],
            "size_stats": {
              "polygons": {
                "count": 162,
                "min_area_m2": 394.70567972084405,
                "max_area_m2": 72723680.46608259,
                "mean_area_m2": 2647392.4130376764,
                "tiny_features": 0
              }
            }
          }
        }
      },
      "test_buildings": {
        "layer_name": "test_buildings",
        "total_features": 93898,
        "passed_checks": 3,
        "failed_checks": 3,
        "warnings": [
          "Column 'name' has 97.3% null values",
          "Column 'height' has 99.6% null values",
          "Found 2 duplicate features",
          "Found 72 polygons smaller than 1.0 m"
        ],
        "success_rate": 50.0,
        "is_valid": false,
        "errors": [
          "Found 92 invalid geometries"
        ],
        "details": {
          "total_features": 93898,
          "crs": {
            "valid": true,
            "errors": [],
            "crs": "EPSG:4326"
          },
          "geometry": {
            "passed": 1,
            "failed": 1,
            "errors": [
              "Found 92 invalid geometries"
            ],
            "warnings": [],
            "invalid_geometries": 92,
            "geometry_types": {
              "Polygon": 93885,
              "MultiPolygon": 13
            },
            "topology_errors": [
              "Feature 126: Self-intersection[9.10001238654642 48.7453956604004]",
              "Feature 165: Ring Self-intersection[9.16446399688721 48.7735443115234]",
              "Feature 817: Self-intersection[9.15743446350098 48.7702941894531]",
              "Feature 1389: Self-intersection[9.16702747344971 48.772216796875]",
              "Feature 5675: Too few points in geometry component[9.10001564025879 48.729808807373]"
            ]
          },
          "attributes": {
            "passed": 0,
            "failed": 0,
            "warnings": [
              "Column 'name' has 97.3% null values",
              "Column 'height' has 99.6% null values"
            ],
            "missing_columns": [],
            "null_counts": {
              "osmid": {
                "count": 0,
                "percentage": 0.0
              },
              "name": {
                "count": 91325,
                "percentage": 97.26
              },
              "building": {
                "count": 0,
                "percentage": 0.0
              },
              "height": {
                "count": 93516,
                "percentage": 99.59
              },
              "area_m2": {
                "count": 0,
                "percentage": 0.0
              },
              "category": {
                "count": 0,
                "percentage": 0.0
              }
            },
            "column_types": {
              "osmid": "int64",
              "name": "object",
              "building": "object",
              "height": "object",
              "area_m2": "float64",
              "category": "object"
            }
          },
          "spatial_extent": {
            "valid": true,
            "warnings": [],
            "actual_bbox": [
              9.100003242492676,
              48.70000076293945,
              9.300000190734863,
              48.79999923706055
            ],
            "expected_bbox": null
          },
          "duplicates": {
            "duplicates": 2,
            "warnings": [
              "Found 2 duplicate features"
            ],
            "duplicate_types": {
              "geometry": 2,
              "osmid": 0
            }
          },
          "feature_sizes": {
            "passed": 0,
            "failed": 1,
            "warnings": [
              "Found 72 polygons smaller than 1.0 m"
            ],
            "size_stats": {
              "polygons": {
                "count": 93898,
                "min_area_m2": 0.0,
                "max_area_m2": 76170.63381906677,
                "mean_area_m2": 174.6350209540855,
                "tiny_features": 72
              }
            }
          }
        }
      },
      "test_cycle": {
        "layer_name": "test_cycle",
        "total_features": 30074,
        "passed_checks": 3,
        "failed_checks": 3,
        "warnings": [
          "Column 'name' has 57.5% null values",
          "Column 'cycleway' has 98.8% null values",
          "Column 'bicycle' has 87.6% null values",
          "Column 'segregated' has 96.0% null values",
          "Found 297 duplicate features",
          "Found 7 lines shorter than 1.0 m"
        ],
        "success_rate": 50.0,
        "is_valid": false,
        "errors": [
          "Found 3 invalid geometries"
        ],
        "details": {
          "total_features": 30074,
          "crs": {
            "valid": true,
            "errors": [],
            "crs": "EPSG:4326"
          },
          "geometry": {
            "passed": 1,
            "failed": 1,
            "errors": [
              "Found 3 invalid geometries"
            ],
            "warnings": [],
            "invalid_geometries": 3,
            "geometry_types": {
              "MultiLineString": 30025,
              "LineString": 49
            },
            "topology_errors": [
              "Feature 5691: Too few points in geometry component[9.18792152404785 48.7511367797852]",
              "Feature 19386: Too few points in geometry component[9.21732044219971 48.7834625244141]",
              "Feature 29133: Too few points in geometry component[9.13847351074219 48.768985748291]"
            ]
          },
          "attributes": {
            "passed": 0,
            "failed": 0,
            "warnings": [
              "Column 'name' has 57.5% null values",
              "Column 'cycleway' has 98.8% null values",
              "Column 'bicycle' has 87.6% null values",
              "Column 'segregated' has 96.0% null values"
            ],
            "missing_columns": [],
            "null_counts": {
              "osmid": {
                "count": 0,
                "percentage": 0.0
              },
              "name": {
                "count": 17285,
                "percentage": 57.47
              },
              "highway": {
                "count": 174,
                "percentage": 0.58
              },
              "cycleway": {
                "count": 29727,
                "percentage": 98.85
              },
              "bicycle": {
                "count": 26348,
                "percentage": 87.61
              },
              "surface": {
                "count": 6305,
                "percentage": 20.96
              },
              "segregated": {
                "count": 28868,
                "percentage": 95.99
              },
              "length_m": {
                "count": 0,
                "percentage": 0.0
              },
              "category": {
                "count": 0,
                "percentage": 0.0
              }
            },
            "column_types": {
              "osmid": "int64",
              "name": "object",
              "highway": "object",
              "cycleway": "object",
              "bicycle": "object",
              "surface": "object",
              "segregated": "object",
              "length_m": "float64",
              "category": "object"
            }
          },
          "spatial_extent": {
            "valid": true,
            "warnings": [],
            "actual_bbox": [
              9.100000381469727,
              48.70000076293945,
              9.29999828338623,
              48.79999923706055
            ],
            "expected_bbox": null
          },
          "duplicates": {
            "duplicates": 297,
            "warnings": [
              "Found 297 duplicate features"
            ],
            "duplicate_types": {
              "geometry": 124,
              "osmid": 173
            }
          },
          "feature_sizes": {
            "passed": 0,
            "failed": 1,
            "warnings": [
              "Found 7 lines shorter than 1.0 m"
            ],
            "size_stats": {
              "lines": {
                "count": 30074,
                "min_length_m": 0.561032170530437,
                "max_length_m": 2101.3024209391547,
                "mean_length_m": 98.67358753717522,
                "tiny_features": 7
              }
            }
          }
        }
      },
      "test_landuse": {
        "layer_name": "test_landuse",
        "total_features": 5870,
        "passed_checks": 3,
        "failed_checks": 3,
        "warnings": [
          "Column 'natural' has 86.0% null values",
          "Found 54 duplicate features",
          "Found 18 polygons smaller than 1.0 m"
        ],
        "success_rate": 50.0,
        "is_valid": false,
        "errors": [
          "Found 30 invalid geometries"
        ],
        "details": {
          "total_features": 5870,
          "crs": {
            "valid": true,
            "errors": [],
            "crs": "EPSG:4326"
          },
          "geometry": {
            "passed": 1,
            "failed": 1,
            "errors": [
              "Found 30 invalid geometries"
            ],
            "warnings": [],
            "invalid_geometries": 30,
            "geometry_types": {
              "Polygon": 5792,
              "MultiPolygon": 78
            },
            "topology_errors": [
              "Feature 198: Self-intersection[9.13001339322475 48.7004850059036]",
              "Feature 237: Self-intersection[9.29990665759485 48.7327125654009]",
              "Feature 511: Self-intersection[9.29988006543011 48.7412493455188]",
              "Feature 762: Self-intersection[9.12187200027348 48.7005858768783]",
              "Feature 1021: Too few points in geometry component[9.22725677490234 48.7013893127441]"
            ]
          },
          "attributes": {
            "passed": 0,
            "failed": 0,
            "warnings": [
              "Column 'natural' has 86.0% null values"
            ],
            "missing_columns": [],
            "null_counts": {
              "osmid": {
                "count": 0,
                "percentage": 0.0
              },
              "landuse": {
                "count": 822,
                "percentage": 14.0
              },
              "natural": {
                "count": 5048,
                "percentage": 86.0
              },
              "area_m2": {
                "count": 0,
                "percentage": 0.0
              },
              "category": {
                "count": 0,
                "percentage": 0.0
              }
            },
            "column_types": {
              "osmid": "int64",
              "landuse": "object",
              "natural": "object",
              "area_m2": "float64",
              "category": "object"
            }
          },
          "spatial_extent": {
            "valid": true,
            "warnings": [],
            "actual_bbox": [
              9.100007057189941,
              48.70000076293945,
              9.299997329711914,
              48.79999923706055
            ],
            "expected_bbox": null
          },
          "duplicates": {
            "duplicates": 54,
            "warnings": [
              "Found 54 duplicate features"
            ],
            "duplicate_types": {
              "geometry": 27,
              "osmid": 27
            }
          },
          "feature_sizes": {
            "passed": 0,
            "failed": 1,
            "warnings": [
              "Found 18 polygons smaller than 1.0 m"
            ],
            "size_stats": {
              "polygons": {
                "count": 5870,
                "min_area_m2": 0.0,
                "max_area_m2": 6190681.348369824,
                "mean_area_m2": 23528.900336446968,
                "tiny_features": 18
              }
            }
          }
        }
      },
      "test_roads": {
        "layer_name": "test_roads",
        "total_features": 21203,
        "passed_checks": 5,
        "failed_checks": 1,
        "warnings": [
          "Column 'lanes' has 74.0% null values",
          "Column 'oneway' has 75.6% null values",
          "Column 'bridge' has 98.6% null values",
          "Column 'tunnel' has 98.4% null values",
          "Column 'access' has 90.8% null values",
          "Found 3 lines shorter than 1.0 m"
        ],
        "success_rate": 83.33,
        "is_valid": true,
        "errors": [],
        "details": {
          "total_features": 21203,
          "crs": {
            "valid": true,
            "errors": [],
            "crs": "EPSG:4326"
          },
          "geometry": {
            "passed": 2,
            "failed": 0,
            "errors": [],
            "warnings": [],
            "invalid_geometries": 0,
            "geometry_types": {
              "MultiLineString": 21203
            },
            "topology_errors": []
          },
          "attributes": {
            "passed": 0,
            "failed": 0,
            "warnings": [
              "Column 'lanes' has 74.0% null values",
              "Column 'oneway' has 75.6% null values",
              "Column 'bridge' has 98.6% null values",
              "Column 'tunnel' has 98.4% null values",
              "Column 'access' has 90.8% null values"
            ],
            "missing_columns": [],
            "null_counts": {
              "osmid": {
                "count": 0,
                "percentage": 0.0
              },
              "name": {
                "count": 9572,
                "percentage": 45.14
              },
              "highway": {
                "count": 0,
                "percentage": 0.0
              },
              "maxspeed": {
                "count": 10279,
                "percentage": 48.48
              },
              "lanes": {
                "count": 15700,
                "percentage": 74.05
              },
              "surface": {
                "count": 4631,
                "percentage": 21.84
              },
              "oneway": {
                "count": 16020,
                "percentage": 75.56
              },
              "bridge": {
                "count": 20909,
                "percentage": 98.61
              },
              "tunnel": {
                "count": 20855,
                "percentage": 98.36
              },
              "access": {
                "count": 19251,
                "percentage": 90.79
              },
              "length_m": {
                "count": 0,
                "percentage": 0.0
              },
              "category": {
                "count": 0,
                "percentage": 0.0
              }
            },
            "column_types": {
              "osmid": "int64",
              "name": "object",
              "highway": "object",
              "maxspeed": "object",
              "lanes": "object",
              "surface": "object",
              "oneway": "object",
              "bridge": "object",
              "tunnel": "object",
              "access": "object",
              "length_m": "float64",
              "category": "object"
            }
          },
          "spatial_extent": {
            "valid": true,
            "warnings": [],
            "actual_bbox": [
              9.100000381469727,
              48.70000076293945,
              9.29999828338623,
              48.79999923706055
            ],
            "expected_bbox": null
          },
          "duplicates": {
            "duplicates": 0,
            "warnings": [],
            "duplicate_types": {
              "geometry": 0,
              "osmid": 0
            }
          },
          "feature_sizes": {
            "passed": 0,
            "failed": 1,
            "warnings": [
              "Found 3 lines shorter than 1.0 m"
            ],
            "size_stats": {
              "lines": {
                "count": 21203,
                "min_length_m": 0.4297925754088691,
                "max_length_m": 2101.3024209391547,
                "mean_length_m": 98.65004793103863,
                "tiny_features": 3
              }
            }
          }
        }
      }
    }
  }
}